{
  "main": {
    "id": "3bfe4381260d94e1",
    "type": "split",
    "children": [
      {
        "id": "9d0023c5a9b3d9aa",
        "type": "tabs",
        "children": [
          {
            "id": "dab46132a40943ec",
            "type": "leaf",
            "state": {
              "type": "markdown",
              "state": {
                "file": "Tree/BST/Validate_BST.md",
                "mode": "source",
                "source": false
              },
              "icon": "lucide-file",
              "title": "Validate_BST"
            }
          }
        ]
      }
    ],
    "direction": "vertical"
  },
  "left": {
    "id": "68afddbd33818778",
    "type": "split",
    "children": [
      {
        "id": "8ded4278c5c2b100",
        "type": "tabs",
        "children": [
          {
            "id": "96cadce104c1fa20",
            "type": "leaf",
            "state": {
              "type": "file-explorer",
              "state": {
                "sortOrder": "alphabetical",
                "autoReveal": false
              },
              "icon": "lucide-folder-closed",
              "title": "Files"
            }
          },
          {
            "id": "c7a58b3f59cbf7b6",
            "type": "leaf",
            "state": {
              "type": "search",
              "state": {
                "query": "",
                "matchingCase": false,
                "explainSearch": false,
                "collapseAll": false,
                "extraContext": false,
                "sortOrder": "alphabetical"
              },
              "icon": "lucide-search",
              "title": "Search"
            }
          },
          {
            "id": "da7e450068028551",
            "type": "leaf",
            "state": {
              "type": "bookmarks",
              "state": {},
              "icon": "lucide-bookmark",
              "title": "Bookmarks"
            }
          }
        ]
      }
    ],
    "direction": "horizontal",
    "width": 300
  },
  "right": {
    "id": "84930ea0c83346f6",
    "type": "split",
    "children": [
      {
        "id": "768f9cd75b3b15b5",
        "type": "tabs",
        "children": [
          {
            "id": "b5b298c6cb6c242d",
            "type": "leaf",
            "state": {
              "type": "backlink",
              "state": {
                "file": "Tree/Delete_Nodes.md",
                "collapseAll": false,
                "extraContext": false,
                "sortOrder": "alphabetical",
                "showSearch": false,
                "searchQuery": "",
                "backlinkCollapsed": false,
                "unlinkedCollapsed": true
              },
              "icon": "links-coming-in",
              "title": "Backlinks for Delete_Nodes"
            }
          },
          {
            "id": "4948fc504a473762",
            "type": "leaf",
            "state": {
              "type": "outgoing-link",
              "state": {
                "file": "Greedy/Greedy.md",
                "linksCollapsed": false,
                "unlinkedCollapsed": true
              },
              "icon": "links-going-out",
              "title": "Outgoing links from Greedy"
            }
          },
          {
            "id": "18bca61180f4b731",
            "type": "leaf",
            "state": {
              "type": "tag",
              "state": {
                "sortOrder": "frequency",
                "useHierarchy": true,
                "showSearch": false,
                "searchQuery": ""
              },
              "icon": "lucide-tags",
              "title": "Tags"
            }
          },
          {
            "id": "5bc09c13e38c250f",
            "type": "leaf",
            "state": {
              "type": "outline",
              "state": {
                "file": "Greedy/Greedy.md",
                "followCursor": false,
                "showSearch": false,
                "searchQuery": ""
              },
              "icon": "lucide-list",
              "title": "Outline of Greedy"
            }
          },
          {
            "id": "43ec33374dd5b9b4",
            "type": "leaf",
            "state": {
              "type": "copilot-chat-view",
              "state": {},
              "icon": "message-square",
              "title": "Copilot"
            }
          }
        ],
        "currentTab": 4
      }
    ],
    "direction": "horizontal",
    "width": 601.5
  },
  "left-ribbon": {
    "hiddenItems": {
      "switcher:Open quick switcher": false,
      "graph:Open graph view": false,
      "canvas:Create new canvas": false,
      "daily-notes:Open today's daily note": false,
      "templates:Insert template": false,
      "command-palette:Open command palette": false,
      "bases:Create new base": false,
      "copilot:Open Copilot Chat": false
    }
  },
  "active": "dab46132a40943ec",
  "lastOpenFiles": [
    "Tree/BST/Insert_into_BST.md",
    "Tree/BST/Return_Kth_Node_BST.md",
    "Tree/BST/Search_in_BST.md",
    "Tree/BST/Validate_BST.md",
    "Tree/Binary_Search_Tree.md",
    "Tree/Binary_Tree.md",
    "Tree/Inorder_Preorder_Postorder.md",
    "Tree/Tree.md",
    "Tree/BST/Delete_Node_BST.md",
    "Tree/BST/Ceil_Floor.md",
    "BST",
    "Vector/Vector.md",
    "README.md",
    "Tree/BST",
    "Tree/Boundary_Traversal.md",
    "Tree/Faltten_BT.md",
    "QuestionOfTheDay/04102025.cpp",
    "QuestionOfTheDay/03102025.cpp",
    "QuestionOfTheDay/02102025.cpp",
    "QuestionOfTheDay/01102025.cpp",
    "QuestionOfTheDay/30092025.cpp",
    "QuestionOfTheDay/29092025.cpp",
    "Tree/ZigZag.md",
    "Tree/Bottom_View.md",
    "copilot/copilot-custom-prompts/Generate table of contents.md",
    "copilot/copilot-custom-prompts/Generate glossary.md",
    "copilot/copilot-custom-prompts/Fix grammar and spelling.md",
    "copilot/copilot-custom-prompts/Explain like I am 5.md",
    "copilot/copilot-custom-prompts/Emojify.md",
    "sc/Pasted image 20250913224532.png",
    "copilot/copilot-custom-prompts/Rewrite as tweet thread.md",
    "copilot/copilot-custom-prompts/Rewrite as tweet.md",
    "copilot/copilot-custom-prompts/Remove URLs.md",
    "copilot/copilot-custom-prompts/Make longer.md",
    "copilot/copilot-custom-prompts/Make shorter.md",
    "copilot/copilot-custom-prompts",
    "copilot"
  ]
}